{
  "section": "2",
  "title": "**Creating Sentient Magic Items**",
  "explicit_references": [
    "Magic Items > Spellcasting",
    "The Planes of Existence > The Material Plane",
    "Appendix MM-A: Miscellaneous > Creatures > Size",
    "Appendix PH-A: Conditions",
    "Attack Rolls and Damage",
    "Appendix PH-B: Fantasy-Historical Pantheons",
    "Equipment",
    "Player's Handbook"
  ],
  "implicit_dependencies": [
    "Using Ability Scores",
    "Combat Step by Step",
    "Beyond 1st Level",
    "Multiclassing"
  ],
  "systems_affected": [
    "Character creation/advancement",
    "Spellcasting",
    "Combat",
    "Items (attunement, uses, etc.)"
  ],
  "rule_text": "## **Creating Sentient Magic Items**\n\nWhen you decide to make a magic item sentient, you create the item's persona in the same way you would create an NPC, with a few exceptions described here.\n",
  "rule_hierarchy": "**Magic Items** > **Creating Sentient Magic Items**"
}