{
  "section": "4",
  "title": "**Tongues**",
  "explicit_references": [
    "Weapon (any sword), very rare (requires attunement)",
    "Player's Handbook",
    "Appears in the spell descriptions",
    "Appears in the descriptions",
    "The Armor table",
    "The Spellcasting ability modifier",
    "The Challenge Rating of 20",
    "Proficiency Bonus by Challenge Rating table",
    "Races Racial Traits",
    "If a weapon has the thrown property, you can throw the weapon to make a ranged attack. If the weapon is a melee weapon",
    "The four Elemental Planes—Air, Earth, Fire, and Water"
  ],
  "implicit_dependencies": [
    "Rules on ability scores and modifiers",
    "Rules on action types",
    "Rules on weapon proficiency",
    "Rules on saving throws",
    "Rules on damage and healing",
    "Rules on the planes of existence.",
    "Rules on spell slots"
  ],
  "systems_affected": [
    "Spellcasting",
    "Combat",
    "Character advancement and customization",
    "Interactions with the environment"
  ],
  "rule_text": "#### **Tongues**\n\n*3rd-level divination*\n\n**Casting Time:** 1 action **Range:** Touch **Components:** V, M (a small clay model of a ziggurat) **Duration:** 1 hour\n\nThis spell grants the creature you touch the ability to understand any spoken language it hears. Moreover, \n\nwhen the target speaks, any creature that knows at least one language and can hear the target understands what it says.\n",
  "rule_hierarchy": "**Spellcasting** > **Tiny Hut** > **Tongues**"
}